swxtools/__init__.py
swxtools/bitmap_tools.py
swxtools/config.py
swxtools/dataframe_tools.py
swxtools/download_tools.py
swxtools/hapi_client.py
swxtools/hapi_knmi_tools.py
swxtools/access/__init__.py
swxtools/access/ace.py
swxtools/access/dscovr.py
swxtools/access/emmert2021_tle_densities.py
swxtools/access/esa_portal_products.py
swxtools/access/esa_session_cookies.py
swxtools/access/flare_class.py
swxtools/access/gfz_kp_hp_indices.py
swxtools/access/goes_xrs.py
swxtools/access/image_mission.py
swxtools/access/msfc_solar_cycle_prediction.py
swxtools/access/penticton_f10.py
swxtools/access/silso_sunspot_number.py
swxtools/access/solarsoft_ace.py
swxtools/access/swarm_diss.py
swxtools/access/swpc_geomagnetic_forecast.py
swxtools/access/swpc_rt.py
swxtools/access/wam_ipe.py
swxtools/access/wam_ipe_download.py
swxtools/orbit/__init__.py
swxtools/orbit/kepler.py
swxtools/orbit/msis.py
swxtools/orbit/tle.py
swxtools/orbit/transforms.py
swxtools-0.0.6.dist-info/METADATA
swxtools-0.0.6.dist-info/WHEEL
swxtools-0.0.6.dist-info/licenses/LICENSE
swxtools-0.0.6.dist-info/RECORD
